README.md
setup.py
XsCore/DataClassBase.py
XsCore/DingRobot.py
XsCore/EmailSender.py
XsCore/Encrypt.py
XsCore/HttpUtils.py
XsCore/IniUtils.py
XsCore/Logger.py
XsCore/RegexUtils.py
XsCore/XsBase64.py
XsCore/XsDateUtils.py
XsCore/XsDialogs.py
XsCore/XsException.py
XsCore/XsJob.py
XsCore/XsJson.py
XsCore/XsPool.py
XsCore/XsStringVal.py
XsCore/XsStrings.py
XsCore/__init__.py
XsCore/Encrypts/AES.py
XsCore/Encrypts/RSA.py
XsCore/Encrypts/__init__.py
XsCore/Encrypts/md5.py
XsCore/XsFso/FileList.py
XsCore/XsFso/FileUtils.py
XsCore/XsFso/XsPath.py
XsCore/XsFso/__init__.py
XsCore/db/DbDal.py
XsCore/db/DbProvider.py
XsCore/db/__init__.py
tests/Base64Test.py
tests/ClassDataTest.py
tests/DingRobotTest.py
tests/EmailSenderTest.py
tests/EncryptTest.py
tests/FileListTest.py
tests/FileUtilsTest.py
tests/LoggerTest.py
tests/StringUtilsTest.py
tests/XsDateUtils.py
tests/XsHttpTest.py
tests/XsIniUtilsTest.py
tests/XsPathTest.py
tests/XsPoolTest.py
tests/XsRegexUtilsTest.py
tests/XsTaskJobTestTest.py
tests/__init__.py
xsCorePy.egg-info/PKG-INFO
xsCorePy.egg-info/SOURCES.txt
xsCorePy.egg-info/dependency_links.txt
xsCorePy.egg-info/requires.txt
xsCorePy.egg-info/top_level.txt