Metadata-Version: 2.1
Name: xsCorePy
Version: 1.0.5
Summary: 模块描述
Home-page: https://github.com/yibo7/xsCorePy
Author: cqs263
Author-email: cqs363@163.com
License: MIT Licence
Keywords: utils,xsCorePy
Platform: any
